periodicity/__init__.py
periodicity/core.py
periodicity/decomposition.py
periodicity/gp.py
periodicity/phase.py
periodicity/spectral.py
periodicity/timefrequency.py
periodicity/data/__init__.py
periodicity-1.0b6.dist-info/LICENSE
periodicity-1.0b6.dist-info/METADATA
periodicity-1.0b6.dist-info/WHEEL
periodicity-1.0b6.dist-info/top_level.txt
periodicity-1.0b6.dist-info/RECORD
