Metadata-Version: 2.1
Name: periodicity
Version: 1.0b6
Summary: Useful tools for periodicity analysis in time series data.
Home-page: https://github.com/dioph/periodicity
Author: Eduardo Nunes
Author-email: dioph@pm.me
License: MIT
Classifier: Programming Language :: Python :: 3
Classifier: License :: OSI Approved :: MIT License
Classifier: Operating System :: OS Independent
Classifier: Intended Audience :: Science/Research
License-File: LICENSE
Requires-Dist: bottleneck
Requires-Dist: celerite2
Requires-Dist: emcee>=3.0
Requires-Dist: george
Requires-Dist: pandas<1.5,>=1.2
Requires-Dist: PyWavelets>=0.5
Requires-Dist: pymc-ext
Requires-Dist: scipy>=1.1
Requires-Dist: tqdm
Requires-Dist: xarray<2022,>=0.20
Provides-Extra: docs
Requires-Dist: jupyter>=1.0; extra == "docs"
Requires-Dist: myst-nb>=0.17; extra == "docs"
Requires-Dist: numpydoc; extra == "docs"
Requires-Dist: pydata-sphinx-theme; extra == "docs"
Provides-Extra: test
Requires-Dist: black==22.3.0; extra == "test"
Requires-Dist: flake8; extra == "test"
Requires-Dist: isort; extra == "test"
Requires-Dist: pytest; extra == "test"
Requires-Dist: pytest-cov; extra == "test"
Requires-Dist: tox; extra == "test"
